setup.py
papermc/__init__.py
papermc.egg-info/PKG-INFO
papermc.egg-info/SOURCES.txt
papermc.egg-info/dependency_links.txt
papermc.egg-info/top_level.txt